django_paystack/__init__.py
django_paystack/admin.py
django_paystack/apps.py
django_paystack/base.py
django_paystack/models.py
django_paystack/signals.py
django_paystack/tests.py
django_paystack/urls.py
django_paystack/views.py
django_paystack/templates/django_paystack/paystack_button.html
django_paystack/templates/django_paystack/sample.htmx
django_paystack/templatetags/__init__.py
django_paystack/templatetags/base.py
django_paystack/templatetags/paystack.py
django_paystack-1.0.0.dist-info/LICENSE
django_paystack-1.0.0.dist-info/METADATA
django_paystack-1.0.0.dist-info/WHEEL
django_paystack-1.0.0.dist-info/top_level.txt
django_paystack-1.0.0.dist-info/RECORD
