Metadata-Version: 2.1
Name: django_paystack
Version: 1.0.0
Summary: Django Paystack Payments package
Home-page: https://github.com/kingnonso/django_paystack
Author: Chinonso Ani
Author-email: achinonso@gmail.com
License: MIT
Keywords: django_paystack
Classifier: Development Status :: 3 - Alpha
Classifier: Framework :: Django :: 3.2
Classifier: Framework :: Django :: 4.2
Classifier: Intended Audience :: Developers
Classifier: License :: OSI Approved :: MIT License
Classifier: Natural Language :: English
Classifier: Programming Language :: Python :: 3
Classifier: Programming Language :: Python :: 3.9
Classifier: Programming Language :: Python :: 3.10
Classifier: Programming Language :: Python :: 3.11
Requires-Python: >=3.9
License-File: LICENSE
Requires-Dist: Django>=3.2
Requires-Dist: pypaystack2==2.0.3
